{
    "address_components": [
        {
            "long_name": "16",
            "short_name": "16",
            "types": [
                "street_number"
            ]
        },
        {
            "long_name": "Yonge Street",
            "short_name": "Yonge St",
            "types": [
                "route"
            ]
        },
        {
            "long_name": "Old Toronto",
            "short_name": "Old Toronto",
            "types": [
                "sublocality_level_1",
                "sublocality",
                "political"
            ]
        },
        {
            "long_name": "Toronto",
            "short_name": "Toronto",
            "types": [
                "locality",
                "political"
            ]
        },
        {
            "long_name": "Toronto Division",
            "short_name": "Toronto Division",
            "types": [
                "administrative_area_level_2",
                "political"
            ]
        },
        {
            "long_name": "Ontario",
            "short_name": "ON",
            "types": [
                "administrative_area_level_1",
                "political"
            ]
        },
        {
            "long_name": "Canada",
            "short_name": "CA",
            "types": [
                "country",
                "political"
            ]
        },
        {
            "long_name": "M5E 2A1",
            "short_name": "M5E 2A1",
            "types": [
                "postal_code"
            ]
        }
    ],
    "adr_address": "Unit E &amp; F, <span class=\"street-address\">16 Yonge St</span>, <span class=\"locality\">Toronto</span>, <span class=\"region\">ON</span> <span class=\"postal-code\">M5E 2A1</span>, <span class=\"country-name\">Canada</span>",
    "formatted_address": "Unit E & F, 16 Yonge St, Toronto, ON M5E 2A1, Canada",
    "formatted_phone_number": "(416) 368-3555",
    "geometry": {
        "location": {
            "lat": 43.6435119,
            "lng": -79.3759025
        },
        "viewport": {
            "northeast": {
                "lat": 43.6448919302915,
                "lng": -79.3744147697085
            },
            "southwest": {
                "lat": 43.6421939697085,
                "lng": -79.3771127302915
            }
        }
    },
    "icon": "https://maps.gstatic.com/mapfiles/place_api/icons/restaurant-71.png",
    "id": "725e62ecd3cd7b020022731782468c3323773320",
    "international_phone_number": "+1 416-368-3555",
    "name": "Subway",
    "opening_hours": {
        "open_now": true,
        "periods": [
            {
                "close": {
                    "day": 0,
                    "time": "2200"
                },
                "open": {
                    "day": 0,
                    "time": "0900"
                }
            },
            {
                "close": {
                    "day": 1,
                    "time": "2230"
                },
                "open": {
                    "day": 1,
                    "time": "0700"
                }
            },
            {
                "close": {
                    "day": 2,
                    "time": "2230"
                },
                "open": {
                    "day": 2,
                    "time": "0700"
                }
            },
            {
                "close": {
                    "day": 3,
                    "time": "2230"
                },
                "open": {
                    "day": 3,
                    "time": "0700"
                }
            },
            {
                "close": {
                    "day": 4,
                    "time": "2230"
                },
                "open": {
                    "day": 4,
                    "time": "0700"
                }
            },
            {
                "close": {
                    "day": 5,
                    "time": "2230"
                },
                "open": {
                    "day": 5,
                    "time": "0700"
                }
            },
            {
                "close": {
                    "day": 6,
                    "time": "2200"
                },
                "open": {
                    "day": 6,
                    "time": "0900"
                }
            }
        ],
        "weekday_text": [
            "Monday: 7:00 AM \u2013 10:30 PM",
            "Tuesday: 7:00 AM \u2013 10:30 PM",
            "Wednesday: 7:00 AM \u2013 10:30 PM",
            "Thursday: 7:00 AM \u2013 10:30 PM",
            "Friday: 7:00 AM \u2013 10:30 PM",
            "Saturday: 9:00 AM \u2013 10:00 PM",
            "Sunday: 9:00 AM \u2013 10:00 PM"
        ]
    },
    "photos": [
        {
            "height": 3187,
            "html_attributions": [
                "<a href=\"https://maps.google.com/maps/contrib/106495783843969090911/photos\">Mike Regier</a>"
            ],
            "photo_reference": "CmRaAAAAtgCvaV_noDSUYdYV6N4LqDwSM66IFUds2Yhj_AZVLx0BIo_naH8okjM5oDjHwjzeTs9kvc-J6k3M96-VEmqgILMcZTPsspjHyOlgC0lq5lOJsN8v21-uoNwLae9vCamFEhAHtbxk_5vm1e_JVzH3PP8YGhTjN8u9aX6JY1asa0dPWathhIng-A",
            "width": 4782
        },
        {
            "height": 4032,
            "html_attributions": [
                "<a href=\"https://maps.google.com/maps/contrib/102553769511302489247/photos\">Android Dave</a>"
            ],
            "photo_reference": "CmRaAAAAEMzRRHsKLXQG5rU9QTpx9YxpkzlF7Z53O-rl4r52PXqfH3cM69s48tM8fpOosUJZ13LybN_L7pt2RflzqWIzWLfFnkIvD2CUkFi64K6GeedSe7vL-VfC1vuC1Rxox5vwEhAdnEyBcLJGXdvvGkgpiGUyGhSivREIozD1h92T2wczz47rxuD8cg",
            "width": 3024
        },
        {
            "height": 3264,
            "html_attributions": [
                "<a href=\"https://maps.google.com/maps/contrib/106495783843969090911/photos\">Mike Regier</a>"
            ],
            "photo_reference": "CmRaAAAA4rGIS-zzjqS1CEKhPKTEMRKaxJU1rASblVfgZ7yteLz7Zny951qJN2k1VRDAyoZU1Fd8jfJzywwGX3shwHJgeuA7WL__ueuEgj7Iz6nsvNg6tWRNXUebDRRNeCNbJNWhEhCPElJuESWReBlTw2eubqRfGhQygCFWnRD0sJq-k1moV5PIpxs55w",
            "width": 4897
        },
        {
            "height": 3109,
            "html_attributions": [
                "<a href=\"https://maps.google.com/maps/contrib/106495783843969090911/photos\">Mike Regier</a>"
            ],
            "photo_reference": "CmRaAAAAHwCS-PyKufGOtxQYXDMtyqQuncWSeu05Bc-PybIM4YedvuwcYmgGDvJsOK_nbW_womBstYC3Y3lHdTsovtgJnTBdL8ACY9Kj6vd1fZC6ReinhfJrJX6dI49gJa4f2YGMEhBkifi8-2Mx1hGHUGsP7mO7GhTUr82tP0IEiy6UsYKi_vYyBq8nlw",
            "width": 4664
        },
        {
            "height": 2448,
            "html_attributions": [
                "<a href=\"https://maps.google.com/maps/contrib/113751359172254525976/photos\">Sergey Alakov</a>"
            ],
            "photo_reference": "CmRaAAAANzPQtczjblmMDxxwrrCabKAzWKvjhcFP3Ua1q5nkPS75ZnCfKgzxOgVN7LOBd03AzxHFwv98Aw-jFipZwEvJcr-0cdNQxf-HHZHZwmSpE4guO5Kqi3AlvKzSY28lmmggEhDRLiBndiBpF7WHbhv0rOL1GhRMrp_8zvJKy-qBDqVw2oYHBS7nwQ",
            "width": 3264
        },
        {
            "height": 604,
            "html_attributions": [
                "<a href=\"https://maps.google.com/maps/contrib/114842505477372159901/photos\">Chen Shaowei</a>"
            ],
            "photo_reference": "CmRaAAAAmeyvkTb7vvMFzxQHbRC6REMU6TD_XQxe1Ta1cike8sr7hUAY4Mt71fgcr1ygW2XTyXiE9rg9MBHbiW01GEywfe_9Z3FeXCKyV_NI_ijYB8WhauBB_zqr8SYf6FmKNP9FEhDWsjcpKDECnP_uNSNmEq33GhQpD52Ls8FuxrpuM0lsng9XV5Unjw",
            "width": 820
        },
        {
            "height": 1518,
            "html_attributions": [
                "<a href=\"https://maps.google.com/maps/contrib/114842505477372159901/photos\">Chen Shaowei</a>"
            ],
            "photo_reference": "CmRaAAAAv49PBpdiVAqAKXERW5pijuIIm84kZdeesAPOdX7J8avGu0CInfDCp8LbGvmt4vnaU4Etdt5Y94fnnXi3AsqMWdR77ZOwv4HuQmRR9j87IgpLreUW3JtwYL9nbBgpdurxEhDcVvyW1WBOJs-x8vkvMV2AGhSNswjG4IglTKLqr5tShgPliabwVg",
            "width": 2048
        },
        {
            "height": 1836,
            "html_attributions": [
                "<a href=\"https://maps.google.com/maps/contrib/112942586853670715121/photos\">Glenn Dickler</a>"
            ],
            "photo_reference": "CmRaAAAALNtPZhvoIqmer8BqJ2dCSvLQd_ARJNKX2zNn5r05mS0jPO506L5ODWndX6660itTXO_Oha6sjRP-zyZ1UovlJOBngGsqpoJD1Jo06qdypY9jmiMlMwnqSnupqyjLNAPqEhCR-lQ02WMOtXGIrWKCmAL3GhR9ArxL2zPOvKqOwAvIRNewxEZo6A",
            "width": 3264
        },
        {
            "height": 4032,
            "html_attributions": [
                "<a href=\"https://maps.google.com/maps/contrib/102553769511302489247/photos\">Android Dave</a>"
            ],
            "photo_reference": "CmRaAAAAXWVHuGMqlTTz33OSCfFvMZIkV1hrzdeVCUbqWWkdIw9MeYroLtiaH-AwFrhRQQgy9pfyOTc3jcLNTs-scIcvwfSeLtlpHlEGNWtuBCriV8nGGWU5SykatrmpnJB42hxoEhDg8DKIDQo8LquSk6_sncI7GhQla1QN55sZTeZcoE56L1BK0FtOYQ",
            "width": 3024
        },
        {
            "height": 960,
            "html_attributions": [
                "<a href=\"https://maps.google.com/maps/contrib/112942586853670715121/photos\">Glenn Dickler</a>"
            ],
            "photo_reference": "CmRaAAAAkIVU-Rc9TqeXzMdPiaJViC9JcRTzfX4bysedmhFkU7VGgffchnF_guVBIbMaN9R12fU3snhBRtbso3I0GIxIsGGsh-ybyPoefJh17EEqNCvpyfy7-9b5SzireRjjWmSAEhDSQI8vDoD31Lq2bl-gnc6kGhS5DFUZUGeEV2P92OAjHvCXpYLNWw",
            "width": 528
        }
    ],
    "place_id": "ChIJrX1m_-oyK4gRtbMIldk2mws",
    "price_level": 1,
    "rating": 3.7,
    "reference": "CmRRAAAAM_9NAJMpqggJNV7ZFkMcTu_yZgOLIQy979BvfBiWzvGeNKI7SkFoX6ukTUZQp0PE7cHtK6v6hJdfIrojsd86R1Zv67g1o2cmplc69NJFv8Kf0QLsHtT1MqyEC60QQQl0EhAGbA_IHJbra4mNKZmniUUEGhRmCATV_HpOWx-gqvELNL6XqgKq8w",
    "reviews": [
        {
            "author_name": "Umar Khan",
            "author_url": "https://www.google.com/maps/contrib/111662318029179451145/reviews",
            "language": "en",
            "profile_photo_url": "https://lh6.googleusercontent.com/-TLGV1YJe-2k/AAAAAAAAAAI/AAAAAAAAAMA/H__PfC4SsIA/s128-c0x00000000-cc-rp-mo-ba4/photo.jpg",
            "rating": 2,
            "relative_time_description": "2 months ago",
            "text": "Food is okay but the people who work there don't even know how to handle food or when and why to change gloves after serving each and every customer and how to avoid cross contamination. Overall, below average",
            "time": 1521903867
        },
        {
            "author_name": "mona r",
            "author_url": "https://www.google.com/maps/contrib/101150772360347988872/reviews",
            "language": "en",
            "profile_photo_url": "https://lh5.googleusercontent.com/-a-8LSFd4yL8/AAAAAAAAAAI/AAAAAAAAADo/OTpX9pOVSIM/s128-c0x00000000-cc-rp-mo-ba3/photo.jpg",
            "rating": 5,
            "relative_time_description": "3 months ago",
            "text": "Quick, clean, friendly.",
            "time": 1520029663
        },
        {
            "author_name": "Elizabeth Hillier",
            "author_url": "https://www.google.com/maps/contrib/109997424046678815064/reviews",
            "language": "en",
            "profile_photo_url": "https://lh3.googleusercontent.com/-2rpUu5TC1bg/AAAAAAAAAAI/AAAAAAAAAJw/gMHQI2R_kjQ/s128-c0x00000000-cc-rp-mo-ba2/photo.jpg",
            "rating": 4,
            "relative_time_description": "6 months ago",
            "text": "Good service. Customer service is average",
            "time": 1512933642
        },
        {
            "author_name": "Yas Abdolmaleki",
            "author_url": "https://www.google.com/maps/contrib/102897115677001302307/reviews",
            "language": "en",
            "profile_photo_url": "https://lh5.googleusercontent.com/-DCuS1qNs0HY/AAAAAAAAAAI/AAAAAAAAAEA/xrByHUPtUmA/s128-c0x00000000-cc-rp-mo-ba5/photo.jpg",
            "rating": 1,
            "relative_time_description": "9 months ago",
            "text": "Small portion, very low quality food and the price is high.",
            "time": 1503503740
        },
        {
            "author_name": "Baljit Singh",
            "author_url": "https://www.google.com/maps/contrib/100766537679855825298/reviews",
            "language": "en",
            "profile_photo_url": "https://lh4.googleusercontent.com/-E3FioLo5_vM/AAAAAAAAAAI/AAAAAAAAAAA/AB6qoq2MS9irwNAaenRKeDD6R9qOAM9AuA/s128-c0x00000000-cc-rp-mo/photo.jpg",
            "rating": 2,
            "relative_time_description": "4 months ago",
            "text": "Fine but not good",
            "time": 1516067241
        }
    ],
    "scope": "GOOGLE",
    "types": [
        "meal_takeaway",
        "restaurant",
        "food",
        "point_of_interest",
        "establishment"
    ],
    "url": "https://maps.google.com/?cid=836322463943537589",
    "utc_offset": -240,
    "vicinity": "Unit E & F, 16 Yonge Street, Toronto",
    "website": "http://www.subway.com/"
}