{
    "address_components": [
        {
            "long_name": "590",
            "short_name": "590",
            "types": [
                "street_number"
            ]
        },
        {
            "long_name": "King Street West",
            "short_name": "King St W",
            "types": [
                "route"
            ]
        },
        {
            "long_name": "Old Toronto",
            "short_name": "Old Toronto",
            "types": [
                "sublocality_level_1",
                "sublocality",
                "political"
            ]
        },
        {
            "long_name": "Toronto",
            "short_name": "Toronto",
            "types": [
                "locality",
                "political"
            ]
        },
        {
            "long_name": "Toronto Division",
            "short_name": "Toronto Division",
            "types": [
                "administrative_area_level_2",
                "political"
            ]
        },
        {
            "long_name": "Ontario",
            "short_name": "ON",
            "types": [
                "administrative_area_level_1",
                "political"
            ]
        },
        {
            "long_name": "Canada",
            "short_name": "CA",
            "types": [
                "country",
                "political"
            ]
        },
        {
            "long_name": "M5V 1M3",
            "short_name": "M5V 1M3",
            "types": [
                "postal_code"
            ]
        }
    ],
    "adr_address": "<span class=\"street-address\">590 King St W</span>, <span class=\"locality\">Toronto</span>, <span class=\"region\">ON</span> <span class=\"postal-code\">M5V 1M3</span>, <span class=\"country-name\">Canada</span>",
    "formatted_address": "590 King St W, Toronto, ON M5V 1M3, Canada",
    "formatted_phone_number": "(416) 366-5959",
    "geometry": {
        "location": {
            "lat": 43.6446256,
            "lng": -79.39969339999999
        },
        "viewport": {
            "northeast": {
                "lat": 43.6459250802915,
                "lng": -79.39832531970849
            },
            "southwest": {
                "lat": 43.64322711970851,
                "lng": -79.40102328029151
            }
        }
    },
    "icon": "https://maps.gstatic.com/mapfiles/place_api/icons/shopping-71.png",
    "id": "8c88d115d47950134917922d1918b9fcab3b6e21",
    "international_phone_number": "+1 416-366-5959",
    "name": "Lee Valley",
    "opening_hours": {
        "open_now": true,
        "periods": [
            {
                "close": {
                    "day": 0,
                    "time": "1700"
                },
                "open": {
                    "day": 0,
                    "time": "1100"
                }
            },
            {
                "close": {
                    "day": 1,
                    "time": "1900"
                },
                "open": {
                    "day": 1,
                    "time": "1000"
                }
            },
            {
                "close": {
                    "day": 2,
                    "time": "1900"
                },
                "open": {
                    "day": 2,
                    "time": "1000"
                }
            },
            {
                "close": {
                    "day": 3,
                    "time": "1900"
                },
                "open": {
                    "day": 3,
                    "time": "1000"
                }
            },
            {
                "close": {
                    "day": 4,
                    "time": "2100"
                },
                "open": {
                    "day": 4,
                    "time": "1000"
                }
            },
            {
                "close": {
                    "day": 5,
                    "time": "2100"
                },
                "open": {
                    "day": 5,
                    "time": "1000"
                }
            },
            {
                "close": {
                    "day": 6,
                    "time": "1800"
                },
                "open": {
                    "day": 6,
                    "time": "0900"
                }
            }
        ],
        "weekday_text": [
            "Monday: 10:00 AM \u2013 7:00 PM",
            "Tuesday: 10:00 AM \u2013 7:00 PM",
            "Wednesday: 10:00 AM \u2013 7:00 PM",
            "Thursday: 10:00 AM \u2013 9:00 PM",
            "Friday: 10:00 AM \u2013 9:00 PM",
            "Saturday: 9:00 AM \u2013 6:00 PM",
            "Sunday: 11:00 AM \u2013 5:00 PM"
        ]
    },
    "photos": [
        {
            "height": 2268,
            "html_attributions": [
                "<a href=\"https://maps.google.com/maps/contrib/101110282007769794565/photos\">Darcy K</a>"
            ],
            "photo_reference": "CmRaAAAA3_w223zvyqv00Zzqq1-0x-1qqY3TsZSJR77vEJF2o1LF5xV4UNBWcv_80nICeZUqeHS226GW3xhuRtgVQIuG5KCRBXkPlLjtrLdGoex-4Srbfr3ZjjA_9GjBEHkMcllgEhDS4dfnVQh9lP-51oQVoOwEGhTjAxg2kkK1nuMdxBGBz7x_nIQ1Yg",
            "width": 4032
        },
        {
            "height": 2340,
            "html_attributions": [
                "<a href=\"https://maps.google.com/maps/contrib/103414693392924430993/photos\">Ian McKenzie</a>"
            ],
            "photo_reference": "CmRaAAAA4Li1p2O8RZiPlRBAgCmoecqNqefkt0YGvcKT9trmrxeJZGkuhZBl4-oPvDcdCh3liZb2Vf2oBwH9_whaOtgC3dIQVB6QKoDzFBIUTO2fUdRdB6y_wR5untV0dm8NvZfaEhC95uhNmcfR87HewuU6YF4xGhSbyd2s8jSu5nMzPi4leXv2Apbj8g",
            "width": 4160
        },
        {
            "height": 2160,
            "html_attributions": [
                "<a href=\"https://maps.google.com/maps/contrib/106098227425648256909/photos\">Andrew Wong</a>"
            ],
            "photo_reference": "CmRaAAAAQvJkbAoEgQKNe93ux-TXBeo4gZvmoUaLKXkyIBzoLdVXuJoKmpYQofJFir_Kt8pElqMvtmhq4zAHZpJhlrZfKW9Hz78LomthslMLGG1wZp33mStJDJ4_UEHAiQ0uIvVpEhBVHmpG2xN0XEwDrprByDt3GhScIJ0aLhGBrLfgFovu3dkPLbfyQw",
            "width": 3840
        },
        {
            "height": 2368,
            "html_attributions": [
                "<a href=\"https://maps.google.com/maps/contrib/117933718800995484882/photos\">jeR D&#39;wayan</a>"
            ],
            "photo_reference": "CmRaAAAAux-8FPP1YN5EQE_KXQsjGB3FjDXDzwydR-7CLn9NaLPOpWP5SQSRGwsbeQMc8y9X5JUJY--CusOYhSwUA7uwQeiQ6LOosWt8ukDvrZ4yZHMkwKyXzfeItq6UMgoljM-2EhDbRtMTdzbYwcdWjJ28SREEGhRHnlhrCHTfOdt10DHd2b80Hc1zYA",
            "width": 4208
        },
        {
            "height": 2368,
            "html_attributions": [
                "<a href=\"https://maps.google.com/maps/contrib/117933718800995484882/photos\">jeR D&#39;wayan</a>"
            ],
            "photo_reference": "CmRaAAAAm4Emomg5WHwO06Cw_fRqc-q6GuRmbPEPHfeOu4ICphoFoBlHxVqe7EQr5QCgKYZGPwxCv-5qmpD9YcUPXVCSvDml0SxvBYWvH8iGupHkjSUzVeMvexUxHVfdnrZghH8sEhApXEgKq2tqo5yScexvjxqeGhSBYT0U_N5q7uyWGE-IZdGvPNX6tA",
            "width": 4208
        },
        {
            "height": 2368,
            "html_attributions": [
                "<a href=\"https://maps.google.com/maps/contrib/117933718800995484882/photos\">jeR D&#39;wayan</a>"
            ],
            "photo_reference": "CmRaAAAA6zKQ-dsI8-QsKuC4hV7n8E8mNWGjMS_V3MqvyokiymkLmiZK0saIj0gkw1q0OliRuH4ySMbTJg0IbvD0w4w2Tc11ksWrxIU_Ysp61Mtvt04ubQljwC7HQvoMm7m5BSJ9EhDIEO-BHs0UQS6MWdiEI2D0GhRcJIOh7jo5B0SstG72Yg6M-PeRyw",
            "width": 4208
        },
        {
            "height": 2268,
            "html_attributions": [
                "<a href=\"https://maps.google.com/maps/contrib/101110282007769794565/photos\">Darcy K</a>"
            ],
            "photo_reference": "CmRaAAAAzKvpBnHw_v2um2UX5T_wr7wKW4H-Nmz06ccP7nesZcC-hxRaIbAX0AA72YthA4jNhZLQ_4JB6Ga2PcEvj_k4eset8zL3msGuyKPJ6pJlIiqsp4db_YSJzgEYRTw7vbg9EhDYAV1b1DDtPrGeZ2QcQGawGhTNkWNrD3pqv_ilRozBFCVRMhbLgg",
            "width": 4032
        },
        {
            "height": 2160,
            "html_attributions": [
                "<a href=\"https://maps.google.com/maps/contrib/106098227425648256909/photos\">Andrew Wong</a>"
            ],
            "photo_reference": "CmRaAAAAgDIcQp2feGLW-MrIZGEdshLbEY_ZOH7njkzD-PWMpY0AK26nhaws6alW4jljdFineQ17D8cOETy2BZ_bPsU6eREKmzFdqsJT7yLc-T5WlWozhuVFZS7BS4cDPZ9-T1hHEhCI0QipgkrM9pi3JBtvWiS4GhTUqhIQ_Z9aUYBx_fRm5MMGaSp8Dw",
            "width": 3840
        },
        {
            "height": 2304,
            "html_attributions": [
                "<a href=\"https://maps.google.com/maps/contrib/105631030389149568365/photos\">Peter Nguyen</a>"
            ],
            "photo_reference": "CmRaAAAAI5L_2wPtZyW0KZhj4gyHKIU2_nxcY9jJgrmcLUq4cTEVVSjHUHqHlABgaIILh-EmWJQbLeEDU2sHLCiltRW_8UcDOWCGfO7fRxLKxDwEWo0VyGQHhEnpdU9t0sdbLrc-EhC1U49lGI013M1y5yrtglrdGhTZZmGTeJrnoaDahQu7Wi7RPODjRQ",
            "width": 4096
        },
        {
            "height": 2368,
            "html_attributions": [
                "<a href=\"https://maps.google.com/maps/contrib/117933718800995484882/photos\">jeR D&#39;wayan</a>"
            ],
            "photo_reference": "CmRaAAAA8dBsT23vJeMJfflTlousdkNf_aFYLnwaO21-w__vZ8fegLmMf6P0DGa-IurwMPONPerakWz5xf1KJAjdpMj5PlmcgGuRuZyOgoVkYRX25tfZUU1R771ftnsXrFGUOamBEhC3nHXpHzA3epC0rBuI4qGRGhTZqs8P1lRaupx8UTJ0lpBZC7iwrQ",
            "width": 4208
        }
    ],
    "place_id": "ChIJqWCV8940K4gRiEAxf0WI_sA",
    "price_level": 3,
    "rating": 4.7,
    "reference": "CmRSAAAAIfviYquqiA-O8MeU2r1L36-XlPkV3Xv8sNLb5eD2J1sc2OQA2IJEitcinHH7g8eFL6gY_1prBdtiyvj5uYRRmptIsVKC4hFTftpnLUke56N15gwEYJsWeG7Vw6Cako9uEhBGierZYsVkvh5d4c4s1eyQGhRiIy7k_5zqaKGjehjIA2nETk99sw",
    "reviews": [
        {
            "author_name": "kristin tran",
            "author_url": "https://www.google.com/maps/contrib/117670187710667483081/reviews",
            "language": "en",
            "profile_photo_url": "https://lh4.googleusercontent.com/-OJYjXIao1uk/AAAAAAAAAAI/AAAAAAAAADg/0uwbARHAv4Y/s128-c0x00000000-cc-rp-mo-ba4/photo.jpg",
            "rating": 5,
            "relative_time_description": "3 months ago",
            "text": "A very spacious place that has plenty of choices for DIY craft or tools for your hobbies. How you order items here is unusual for many people (but it's a simple process), so ask an employee if you've never been here before or never even stepped foot onto a tool store. The employees are very generous for even first timers so don't fret about asking and just follow their easy instructions on purchasing.",
            "time": 1519961193
        },
        {
            "author_name": "Eric Malcolmson",
            "author_url": "https://www.google.com/maps/contrib/116055847066017522598/reviews",
            "language": "en",
            "profile_photo_url": "https://lh4.googleusercontent.com/-Eq_-X2dF9p0/AAAAAAAAAAI/AAAAAAAAACo/wmh-cMzRJ7k/s128-c0x00000000-cc-rp-mo/photo.jpg",
            "rating": 5,
            "relative_time_description": "a month ago",
            "text": "Great stuff, great service, great ideas. Don't let anyone tell you it's expensive. They only sell good stuff and if there's a problem they take care of it",
            "time": 1524785075
        },
        {
            "author_name": "Dennis Fowler",
            "author_url": "https://www.google.com/maps/contrib/109171852179114299841/reviews",
            "language": "en",
            "profile_photo_url": "https://lh5.googleusercontent.com/-JxE_J8QV3HU/AAAAAAAAAAI/AAAAAAAAAAA/AB6qoq2quB7i5DO4bIXU1itHbAdtIRo9Fg/s128-c0x00000000-cc-rp-mo-ba4/photo.jpg",
            "rating": 5,
            "relative_time_description": "in the last week",
            "text": "Awesome tools, high quality, great service. I highly recommend",
            "time": 1528565204
        },
        {
            "author_name": "Ian McKenzie",
            "author_url": "https://www.google.com/maps/contrib/103414693392924430993/reviews",
            "language": "en",
            "profile_photo_url": "https://lh3.googleusercontent.com/-CYmkTQaK7Lc/AAAAAAAAAAI/AAAAAAAAACs/VE-P_A413ms/s128-c0x00000000-cc-rp-mo-ba5/photo.jpg",
            "rating": 5,
            "relative_time_description": "4 months ago",
            "text": "Awesome selection of woodworking/gardening tools and accessories. For me, browsing this place was as good as attending a movie. Looks like they have woodworking seminars too which I will definitely be checking out.",
            "time": 1518296788
        },
        {
            "author_name": "Jennifer Cote",
            "author_url": "https://www.google.com/maps/contrib/113975614563386111446/reviews",
            "language": "en",
            "profile_photo_url": "https://lh5.googleusercontent.com/-pUi55le-amk/AAAAAAAAAAI/AAAAAAAAAvo/RFHZVshW9Vw/s128-c0x00000000-cc-rp-mo-ba4/photo.jpg",
            "rating": 5,
            "relative_time_description": "5 months ago",
            "text": "If you have a creative mind, walking through this store feels nothing short of inspirational. The staff treat you like family and the selection is beyond your imagination. \nWoodworking heaven.",
            "time": 1515085706
        }
    ],
    "scope": "GOOGLE",
    "types": [
        "hardware_store",
        "furniture_store",
        "home_goods_store",
        "store",
        "point_of_interest",
        "establishment"
    ],
    "url": "https://maps.google.com/?cid=13906702531434725512",
    "utc_offset": -240,
    "vicinity": "590 King Street West, Toronto",
    "website": "http://www.leevalley.com/home/page.aspx?p=53697&cat="
}